or_af/__init__.py
or_af/a2a/__init__.py
or_af/a2a/compatibility.py
or_af/a2a/protocol.py
or_af/callbacks/__init__.py
or_af/callbacks/handlers.py
or_af/core/__init__.py
or_af/core/agent.py
or_af/core/tool.py
or_af/exceptions/__init__.py
or_af/mcp/__init__.py
or_af/mcp/client.py
or_af/mcp/server.py
or_af/models/__init__.py
or_af/models/agent_models.py
or_af/models/event_models.py
or_af/models/message_models.py
or_af/models/tool_models.py
or_af/utils/__init__.py
or_af/utils/logger.py
or_af/workflow/__init__.py
or_af/workflow/builders.py
or_af/workflow/graph.py
or_af/workflow/nodes.py
or_af/workflow/visualization.py
or_af-0.4.0.dist-info/LICENSE
or_af-0.4.0.dist-info/METADATA
or_af-0.4.0.dist-info/WHEEL
or_af-0.4.0.dist-info/top_level.txt
or_af-0.4.0.dist-info/RECORD
