Metadata-Version: 2.1
Name: or-af
Version: 0.4.0
Summary: Operations Research Agentic Framework - A powerful framework for creating AI agent workflows with official MCP and A2A protocol SDKs
Author-email: OR-AF Team <aakashroyiitb@gmail.com>
License: MIT
Project-URL: Homepage, https://github.com/iaakashRoy/or-af
Project-URL: Documentation, https://github.com/iaakashRoy/or-af#readme
Project-URL: Repository, https://github.com/iaakashRoy/or-af
Project-URL: Bug Tracker, https://github.com/iaakashRoy/or-af/issues
Keywords: operations research,ai,agent,llm,openai,tools,framework,optimization,mcp,workflow,a2a,multi-agent
Classifier: Development Status :: 4 - Beta
Classifier: Intended Audience :: Developers
Classifier: Topic :: Software Development :: Libraries :: Python Modules
Classifier: Topic :: Scientific/Engineering :: Artificial Intelligence
Classifier: Programming Language :: Python :: 3
Classifier: Programming Language :: Python :: 3.10
Classifier: Programming Language :: Python :: 3.11
Classifier: Programming Language :: Python :: 3.12
Classifier: Programming Language :: Python :: 3.13
Requires-Python: >=3.10
License-File: LICENSE
Requires-Dist: openai>=1.0.0
Requires-Dist: python-dotenv>=1.0.0
Requires-Dist: pydantic>=2.0.0
Requires-Dist: mcp[cli]>=1.2.0
Requires-Dist: a2a-sdk[http-server]>=0.3.0
Requires-Dist: httpx>=0.23.0
Provides-Extra: all
Requires-Dist: a2a-sdk[all]>=0.3.0; extra == "all"
Provides-Extra: dev
Requires-Dist: pytest>=7.0.0; extra == "dev"
Requires-Dist: black>=23.0.0; extra == "dev"
Requires-Dist: flake8>=6.0.0; extra == "dev"
Requires-Dist: mypy>=1.0.0; extra == "dev"
